datanews/__init__.py
datanews/requestor.py
datanews/api_resources/__init__.py
datanews/api_resources/monitor.py
datanews/api_resources/news.py
datanews-0.0.7.dist-info/LICENSE
datanews-0.0.7.dist-info/METADATA
datanews-0.0.7.dist-info/WHEEL
datanews-0.0.7.dist-info/top_level.txt
datanews-0.0.7.dist-info/RECORD
