Metadata-Version: 2.1
Name: datanews
Version: 0.0.7
Summary: Python client library for Datanews API
Home-page: https://github.com/DatanewsOrg/datanews-python
Author: Vladyslav Mokrousov
Author-email: mokrousov@datanews.io
License: UNKNOWN
Platform: UNKNOWN
Classifier: Programming Language :: Python :: 3
Classifier: License :: OSI Approved :: MIT License
Classifier: Operating System :: OS Independent
Requires-Python: >=3.5
